symqc/__init__.py
symqc/__main__.py
symqc/simulator.py
symqc/kernel/__init__.py
symqc/kernel/circuit.py
symqc/kernel/gate.py
symqc/kernel/gates_lib.py
symqc/kernel/qubit.py
symqc/kernel/qubit_name_manager.py
symqc/kernel/utils.py
symqc/kernel/ket/__init__.py
symqc/kernel/ket/entanglement.py
symqc/kernel/ket/qubit.py
symqc/kernel/ket/state.py
symqc/kernel/ket/store.py
symqc/output/__init__.py
symqc/output/store.py
symqc/output/symbol_map.py
symqc/qcis/__init__.py
symqc/qcis/instr.py
symqc/qcis/lexer.py
symqc/qcis/parser.py
symqc-1.1.1.dist-info/LICENSE
symqc-1.1.1.dist-info/METADATA
symqc-1.1.1.dist-info/WHEEL
symqc-1.1.1.dist-info/top_level.txt
symqc-1.1.1.dist-info/RECORD
