Metadata-Version: 2.1
Name: symqc
Version: 1.1.1
Summary: Symbolic Quantum Computing Simulator
Home-page: https://gitee.com/quingo/SymQc
Author: V♂n
Author-email: huangzixiao@nudt.edu.cn
Project-URL: Bug Tracker, https://gitee.com/quingo/SymQc/issues
Classifier: Programming Language :: Python :: 3 :: Only
Classifier: License :: OSI Approved :: Apache Software License
Classifier: Operating System :: OS Independent
Requires-Python: >=3.8
License-File: LICENSE
Requires-Dist: sympy
Requires-Dist: ply
Requires-Dist: numpy
